aminofixfix/__init__.py
aminofixfix/acm.py
aminofixfix/client.py
aminofixfix/socket.py
aminofixfix/sub_client.py
aminofixfix/asyncfixfix/README.md
aminofixfix/asyncfixfix/__init__.py
aminofixfix/asyncfixfix/acm.py
aminofixfix/asyncfixfix/client.py
aminofixfix/asyncfixfix/socket.py
aminofixfix/asyncfixfix/sub_client.py
aminofixfix/lib/__init__.py
aminofixfix/lib/exceptions.py
aminofixfix/lib/headers.py
aminofixfix/lib/helpers.py
aminofixfix/lib/objects.py
aminofixfix/lib/facades/__init__.py
aminofixfix/lib/facades/aiohttp.py
aminofixfix/lib/facades/async_httpx.py
aminofixfix/lib/facades/requests.py
aminofixfix/lib/facades/sync_httpx.py
aminofixfix/lib/facades/unsuccessful_import.py
amino_fix_fix-1.2.0.dist-info/METADATA
amino_fix_fix-1.2.0.dist-info/WHEEL
amino_fix_fix-1.2.0.dist-info/licenses/LICENSE
amino_fix_fix-1.2.0.dist-info/RECORD
