Metadata-Version: 2.3
Name: amino.fix.fix
Version: 1.2.0
Summary: Unofficial library to work with Aminoapps
Project-URL: Download, https://github.com/imperialwool/Amino.fix.fix.git
Project-URL: Homepage, https://github.com/imperialwool/Amino.fix.fix
Project-URL: Issues, https://github.com/imperialwool/Amino.fix.fix/issues
Author-email: imperialwool <hi@iwool.dev>
License-Expression: MIT
License-File: LICENSE
Keywords: amino,amino fix,amino fix fix,amino py,amino-bot,amino.fix,amino.fix.fix,aminoapps,aminofix,aminofixfix,api,imperialwool,medialab,minori,narvii,ndc,python,python3,python3.x
Classifier: Intended Audience :: Developers
Classifier: License :: OSI Approved :: MIT License
Classifier: Programming Language :: Python
Classifier: Programming Language :: Python :: 3 :: Only
Classifier: Programming Language :: Python :: 3.8
Classifier: Programming Language :: Python :: 3.9
Classifier: Programming Language :: Python :: 3.10
Classifier: Programming Language :: Python :: 3.11
Classifier: Programming Language :: Python :: 3.12
Classifier: Programming Language :: Python :: 3.13
Requires-Python: >=3.8
Requires-Dist: httpx>=0.27.0
Requires-Dist: httpx[http2]
Requires-Dist: httpx[socks]
Requires-Dist: python-socks
Requires-Dist: websocket-client>=1.3.1
Provides-Extra: aiohttp
Requires-Dist: aiohttp-socks; extra == 'aiohttp'
Requires-Dist: aiohttp>=3.9.0; extra == 'aiohttp'
Requires-Dist: aiohttp[speedups]; extra == 'aiohttp'
Provides-Extra: dev
Requires-Dist: build; extra == 'dev'
Requires-Dist: hatch; extra == 'dev'
Requires-Dist: twine; extra == 'dev'
Requires-Dist: wheel; extra == 'dev'
Provides-Extra: requests
Requires-Dist: requests>=2.30.0; extra == 'requests'
Requires-Dist: requests[socks]; extra == 'requests'
